odoo/addons/account_invoice_comment_template/README.rst
odoo/addons/account_invoice_comment_template/__init__.py
odoo/addons/account_invoice_comment_template/__manifest__.py
odoo/addons/account_invoice_comment_template/i18n/account_invoice_comment_template.pot
odoo/addons/account_invoice_comment_template/i18n/ar.po
odoo/addons/account_invoice_comment_template/i18n/bg.po
odoo/addons/account_invoice_comment_template/i18n/bs.po
odoo/addons/account_invoice_comment_template/i18n/ca.po
odoo/addons/account_invoice_comment_template/i18n/cs.po
odoo/addons/account_invoice_comment_template/i18n/de.po
odoo/addons/account_invoice_comment_template/i18n/el_GR.po
odoo/addons/account_invoice_comment_template/i18n/en_GB.po
odoo/addons/account_invoice_comment_template/i18n/es.po
odoo/addons/account_invoice_comment_template/i18n/es_CR.po
odoo/addons/account_invoice_comment_template/i18n/es_EC.po
odoo/addons/account_invoice_comment_template/i18n/es_MX.po
odoo/addons/account_invoice_comment_template/i18n/et.po
odoo/addons/account_invoice_comment_template/i18n/fi.po
odoo/addons/account_invoice_comment_template/i18n/fr.po
odoo/addons/account_invoice_comment_template/i18n/fr_CA.po
odoo/addons/account_invoice_comment_template/i18n/fr_CH.po
odoo/addons/account_invoice_comment_template/i18n/fr_FR.po
odoo/addons/account_invoice_comment_template/i18n/gl.po
odoo/addons/account_invoice_comment_template/i18n/hr.po
odoo/addons/account_invoice_comment_template/i18n/hr_HR.po
odoo/addons/account_invoice_comment_template/i18n/hu.po
odoo/addons/account_invoice_comment_template/i18n/id.po
odoo/addons/account_invoice_comment_template/i18n/invoice_comment_template.pot
odoo/addons/account_invoice_comment_template/i18n/it.po
odoo/addons/account_invoice_comment_template/i18n/ja.po
odoo/addons/account_invoice_comment_template/i18n/lt.po
odoo/addons/account_invoice_comment_template/i18n/mk.po
odoo/addons/account_invoice_comment_template/i18n/mn.po
odoo/addons/account_invoice_comment_template/i18n/nb.po
odoo13_addon_account_invoice_comment_template-13.0.1.1.1.dist-info/METADATA
odoo13_addon_account_invoice_comment_template-13.0.1.1.1.dist-info/WHEEL
odoo13_addon_account_invoice_comment_template-13.0.1.1.1.dist-info/top_level.txt
odoo13_addon_account_invoice_comment_template-13.0.1.1.1.dist-info/RECORD
