Metadata-Version: 2.1
Name: odoo13-addon-account-invoice-comment-template
Version: 13.0.1.1.1
Summary: Comments templates on invoice documents
Home-page: UNKNOWN
Author: Camptocamp, Tecnativa, Odoo Community Association (OCA)
Author-email: support@odoo-community.org
License: AGPL-3
Platform: UNKNOWN
Classifier: Programming Language :: Python
Classifier: Framework :: Odoo
Classifier: License :: OSI Approved :: GNU Affero General Public License v3
Classifier: Development Status :: 6 - Mature
Requires-Python: >=3.5
Requires-Dist: odoo13-addon-base-comment-template
Requires-Dist: odoo (<13.1dev,>=13.0a)
